satvis/__init__.py
satvis/int_tree_converter.py
satvis/schedule_plots.py
satvis/vis_history.py
satvis/visibility_func.py
satvis-0.2.4.dist-info/LICENSE
satvis-0.2.4.dist-info/METADATA
satvis-0.2.4.dist-info/WHEEL
satvis-0.2.4.dist-info/top_level.txt
satvis-0.2.4.dist-info/RECORD
