Metadata-Version: 2.1
Name: satvis
Version: 0.2.4
Summary: Satellite LOS visibility calculator
Author-email: Dylan Penn <dylan.penn@vt.edu>
License: MIT License
Project-URL: Homepage, https://github.com/dylan906/satvis
Classifier: Programming Language :: Python :: 2
Classifier: License :: OSI Approved :: MIT License
Classifier: Operating System :: OS Independent
Requires-Python: >=2.8.5
License-File: LICENSE
Requires-Dist: matplotlib >=3.5
Requires-Dist: intervaltree >=3.1
Requires-Dist: numpy
Provides-Extra: dev
Requires-Dist: flake8 ; extra == 'dev'
Requires-Dist: pylint ; extra == 'dev'
Requires-Dist: pytest ; extra == 'dev'
Requires-Dist: flake8-bugbear ==22.4.25 ; extra == 'dev'
Requires-Dist: flake8-builtins ==1.5.3 ; extra == 'dev'
Requires-Dist: flake8-docstrings ==1.6.0 ; extra == 'dev'
Requires-Dist: flake8-plugin-utils ==1.3.2 ; extra == 'dev'
Requires-Dist: flake8-pytest-style ==1.6.0 ; extra == 'dev'
Requires-Dist: flake8-rst-docstrings ==0.2.6 ; extra == 'dev'
Requires-Dist: black >=22.3.0 ; extra == 'dev'
Requires-Dist: isort[colors] ; extra == 'dev'
